CHANGELOG.md
LICENSE
README.md
pyproject.toml
synch/__init__.py
synch/broker/__init__.py
synch/broker/kafka.py
synch/broker/redis.py
synch/cli.py
synch/common.py
synch/convert.py
synch/enums.py
synch/exceptions.py
synch/factory.py
synch/reader/__init__.py
synch/reader/mysql.py
synch/reader/postgres.py
synch/redis_mixin.py
synch/replication/__init__.py
synch/replication/continuous.py
synch/replication/etl.py
synch/settings.py
synch/writer/__init__.py
synch/writer/collapsing_merge_tree.py
synch/writer/merge_tree.py
synch/writer/replacing_merge_tree.py
synch/writer/versioned_collapsing_merge_tree.py
synch-0.7.2.dist-info/entry_points.txt
synch-0.7.2.dist-info/LICENSE
synch-0.7.2.dist-info/WHEEL
synch-0.7.2.dist-info/METADATA
synch-0.7.2.dist-info/RECORD
