Metadata-Version: 2.1
Name: synch
Version: 0.7.2
Summary: Sync data from other DB to ClickHouse, current support postgres and mysql, and support full and increment ETL.
Home-page: https://github.com/long2ice/synch
License: Apache-2.0
Keywords: MySQL,ClickHouse,Sync,replication
Author: long2ice
Author-email: long2ice@gmail.com
Requires-Python: >=3.7,<4.0
Classifier: License :: OSI Approved :: Apache Software License
Classifier: Programming Language :: Python :: 3
Classifier: Programming Language :: Python :: 3.7
Classifier: Programming Language :: Python :: 3.8
Classifier: Programming Language :: Python :: 3.9
Requires-Dist: click
Requires-Dist: clickhouse-driver
Requires-Dist: kafka-python
Requires-Dist: loguru
Requires-Dist: mysql-replication
Requires-Dist: mysqlclient
Requires-Dist: mysqlparse
Requires-Dist: psycopg2
Requires-Dist: pymysql (<1.0.0)
Requires-Dist: python-dateutil
Requires-Dist: pyyaml
Requires-Dist: ratelimitingfilter
Requires-Dist: redis
Project-URL: Documentation, https://github.com/long2ice/synch
Project-URL: Repository, https://github.com/long2ice/synch.git
